ccxt/__init__.py
ccxt/acx.py
ccxt/anxpro.py
ccxt/aofex.py
ccxt/bcex.py
ccxt/bequant.py
ccxt/bibox.py
ccxt/bigone.py
ccxt/binance.py
ccxt/binanceje.py
ccxt/binanceus.py
ccxt/bit2c.py
ccxt/bitbank.py
ccxt/bitbay.py
ccxt/bitfinex.py
ccxt/bitfinex2.py
ccxt/bitflyer.py
ccxt/bitforex.py
ccxt/bithumb.py
ccxt/bitkk.py
ccxt/bitmart.py
ccxt/bitmax.py
ccxt/bitmex.py
ccxt/bitpanda.py
ccxt/bitso.py
ccxt/bitstamp.py
ccxt/bitstamp1.py
ccxt/bittrex.py
ccxt/bitvavo.py
ccxt/bitz.py
ccxt/bl3p.py
ccxt/bleutrade.py
ccxt/braziliex.py
ccxt/btcalpha.py
ccxt/btcbox.py
ccxt/btcmarkets.py
ccxt/btctradeua.py
ccxt/btcturk.py
ccxt/buda.py
ccxt/bw.py
ccxt/bybit.py
ccxt/bytetrade.py
ccxt/cex.py
ccxt/chilebit.py
ccxt/coinbase.py
ccxt/coinbaseprime.py
ccxt/coinbasepro.py
ccxt/coincheck.py
ccxt/coinegg.py
ccxt/coinex.py
ccxt/coinfalcon.py
ccxt/coinfloor.py
ccxt/coingi.py
ccxt/coinmarketcap.py
ccxt/coinmate.py
ccxt/coinone.py
ccxt/coinspot.py
ccxt/coss.py
ccxt/crex24.py
ccxt/currencycom.py
ccxt/deribit.py
ccxt/digifinex.py
ccxt/dsx.py
ccxt/eterbase.py
ccxt/exmo.py
ccxt/exx.py
ccxt/fcoin.py
ccxt/fcoinjp.py
ccxt/flowbtc.py
ccxt/foxbit.py
ccxt/ftx.py
ccxt/fybse.py
ccxt/gateio.py
ccxt/gemini.py
ccxt/hbtc.py
ccxt/hitbtc.py
ccxt/hollaex.py
ccxt/huobijp.py
ccxt/huobipro.py
ccxt/huobiru.py
ccxt/ice3x.py
ccxt/idex.py
ccxt/independentreserve.py
ccxt/indodax.py
ccxt/itbit.py
ccxt/kraken.py
ccxt/kucoin.py
ccxt/kuna.py
ccxt/lakebtc.py
ccxt/latoken.py
ccxt/lbank.py
ccxt/liquid.py
ccxt/livecoin.py
ccxt/luno.py
ccxt/lykke.py
ccxt/mercado.py
ccxt/mixcoins.py
ccxt/oceanex.py
ccxt/okcoin.py
ccxt/okex.py
ccxt/paymium.py
ccxt/phemex.py
ccxt/poloniex.py
ccxt/probit.py
ccxt/qtrade.py
ccxt/rightbtc.py
ccxt/southxchange.py
ccxt/stex.py
ccxt/stronghold.py
ccxt/surbitcoin.py
ccxt/therock.py
ccxt/tidebit.py
ccxt/tidex.py
ccxt/timex.py
ccxt/upbit.py
ccxt/vaultoro.py
ccxt/vbtc.py
ccxt/wavesexchange.py
ccxt/whitebit.py
ccxt/xbtce.py
ccxt/xena.py
ccxt/yobit.py
ccxt/zaif.py
ccxt/zb.py
ccxt/async_support/__init__.py
teatien_ccxt-2.0.6.dist-info/LICENSE.txt
teatien_ccxt-2.0.6.dist-info/METADATA
teatien_ccxt-2.0.6.dist-info/WHEEL
teatien_ccxt-2.0.6.dist-info/top_level.txt
teatien_ccxt-2.0.6.dist-info/RECORD
