Metadata-Version: 2.1
Name: teatien-ccxt
Version: 2.0.6
Summary: A JavaScript / Python / PHP cryptocurrency trading library with support for 130+ exchanges
Home-page: https://ccxt.trade
Author: Igor Kroitor
Author-email: igor.kroitor@gmail.com
License: MIT
Keywords: algorithmic,algotrading,altcoin,altcoins,api,arbitrage,real-time,realtime,backtest,backtesting,bitcoin,bot,btc,cny,coin,coins,crypto,cryptocurrency,crypto currency,crypto market,currency,currencies,darkcoin,dash,digital currency,doge,dogecoin,e-commerce,etc,eth,ether,ethereum,exchange,exchanges,eur,framework,invest,investing,investor,library,light,litecoin,ltc,market,market data,markets,merchandise,merchant,minimal,ohlcv,order,orderbook,order book,price,price data,pricefeed,private,pub
Platform: UNKNOWN
Classifier: Development Status :: 4 - Beta
Classifier: Intended Audience :: Developers
Classifier: Intended Audience :: Financial and Insurance Industry
Classifier: Intended Audience :: Information Technology
Classifier: Topic :: Software Development :: Build Tools
Classifier: Topic :: Office/Business :: Financial :: Investment
Classifier: License :: OSI Approved :: MIT License
Classifier: Programming Language :: Python :: 2
Classifier: Programming Language :: Python :: 2.7
Classifier: Programming Language :: Python :: 3
Classifier: Programming Language :: Python :: 3.3
Classifier: Programming Language :: Python :: 3.4
Classifier: Programming Language :: Python :: 3.5
Classifier: Programming Language :: Python :: 3.6
Classifier: Programming Language :: JavaScript
Classifier: Programming Language :: PHP
Classifier: Operating System :: OS Independent
Classifier: Environment :: Console
Requires-Dist: setuptools (>=38.5.1)
Requires-Dist: certifi (>=2018.1.18)
Requires-Dist: requests (>=2.18.4)
Requires-Dist: cryptography (>=2.6.1)
Requires-Dist: aiohttp (==3.6.2) ; python_version>="3.5.2"
Requires-Dist: aiodns (==1.1.1) ; python_version>="3.5.2"
Requires-Dist: yarl (==1.1.0) ; python_version>="3.5.2"
Provides-Extra: doc
Requires-Dist: Sphinx (==1.7.0) ; extra == 'doc'
Provides-Extra: qa
Requires-Dist: flake8 (==3.7.9) ; extra == 'qa'
